{
	"pages": [
		{
			"path": "pages/index/index",
			"style": {
				"navigationStyle":"custom",
				"usingComponents": {
					"van-grid": "/wxcomponents/vant-weapp/grid/index",
					"van-grid-item": "/wxcomponents/vant-weapp/grid-item/index",
					"van-dropdown-menu": "/wxcomponents/vant-weapp/dropdown-menu/index",
					"van-dropdown-item": "/wxcomponents/vant-weapp/dropdown-item/index",
					"van-popup": "/wxcomponents/vant-weapp/popup/index",
					"van-icon": "/wxcomponents/vant-weapp/icon/index",
					"van-slider": "/wxcomponents/vant-weapp/slider/index"
				}
			}
		},
		{
			"path":"pages/login/login",
			"style": {
				"navigationBarTitleText":"登录"
			}
		},
		{
			"path":"pages/web/web-view",
			"style": {
				"navigationBarTitleText":"网页"
			}
		}
	],
	"globalStyle": {
		"navigationBarTextStyle": "black",
		"navigationBarTitleText": "SteyIoT",
		"navigationBarBackgroundColor": "#FAFAFA",
		"backgroundColor": "#FFFFFF"
	}
}
